gradio_toggle/__init__.py
gradio_toggle/toggle.py
gradio_toggle/toggle.pyi
gradio_toggle/templates/component/index.js
gradio_toggle/templates/component/style.css
gradio_toggle/templates/example/index.js
gradio_toggle/templates/example/style.css
gradio_toggle-2.0.2.dist-info/METADATA
gradio_toggle-2.0.2.dist-info/WHEEL
gradio_toggle-2.0.2.dist-info/RECORD
