Metadata-Version: 2.3
Name: gradio_toggle
Version: 2.0.2
Summary: A custom Gradio component that toggles between on and off states.
Project-URL: Changelog, https://github.com/dwancin/gradio-toggle/releases
Project-URL: Repository, https://github.com/dwancin/gradio-toggle
Project-URL: Space, https://huggingface.co/spaces/dwancin/gradio_toggle
Author: Daniel Ialcin Misser Westergaard
License-Expression: Apache-2.0
Keywords: gradio,gradio-custom-component,gradio-template-Checkbox,gradio-toggle
Classifier: Development Status :: 3 - Alpha
Classifier: Operating System :: OS Independent
Classifier: Programming Language :: Python :: 3
Classifier: Programming Language :: Python :: 3 :: Only
Classifier: Programming Language :: Python :: 3.8
Classifier: Programming Language :: Python :: 3.9
Classifier: Programming Language :: Python :: 3.10
Classifier: Programming Language :: Python :: 3.11
Classifier: Topic :: Scientific/Engineering
Classifier: Topic :: Scientific/Engineering :: Artificial Intelligence
Classifier: Topic :: Scientific/Engineering :: Visualization
Requires-Python: >=3.10
Requires-Dist: gradio<6.0,>=4.0
Provides-Extra: dev
Requires-Dist: build; extra == 'dev'
Requires-Dist: twine; extra == 'dev'
